google_currency/__init__.py
google_currency-1.0.9.dist-info/LICENSE
google_currency-1.0.9.dist-info/METADATA
google_currency-1.0.9.dist-info/WHEEL
google_currency-1.0.9.dist-info/top_level.txt
google_currency-1.0.9.dist-info/RECORD
