Metadata-Version: 2.1
Name: google_currency
Version: 1.0.9
Summary: A simple library to convert the currency of one country to other, it supports 153 countries' currency
Home-page: https://github.com/om06/google-currency
Author: Hariom Tiwari
Author-email: hariom.tiwari.006@gmail.com
License: UNKNOWN
Platform: UNKNOWN
Classifier: Programming Language :: Python :: 3
Classifier: License :: OSI Approved :: MIT License
Classifier: Operating System :: OS Independent
Classifier: Intended Audience :: Developers
License-File: LICENSE
